[
  {
    "path": "내추럴/아우터/1.jpg",
    "category": "outerwear",
    "name": "Black Leather Jacket",
    "color": "black",
    "style": "casual",
    "gender": "female",
    "bodyShape": "natural",
    "length": "normal",
    "clothingPrompt": "wearing a black leather jacket, casual or chic style, with a classic collar"
  },
  {
    "path": "내추럴/아우터/2.jpg",
    "category": "outerwear",
    "name": "Blue Denim Jacket with Pockets",
    "color": "blue",
    "style": "casual",
    "gender": "female",
    "bodyShape": "natural",
    "length": "normal",
    "clothingPrompt": "wearing a blue denim jacket with four front pockets, casual style"
  },
  {
    "path": "내추럴/아우터/3.jpg",
    "category": "outerwear",
    "name": "Black Tweed Jacket with Silver Buttons",
    "color": "black",
    "style": "elegant",
    "gender": "female",
    "bodyShape": "natural",
    "length": "normal",
    "clothingPrompt": "wearing a black tweed jacket with a round neck, silver buttons, and frayed edges, elegant and classic style"
  },
  {
    "path": "내추럴/아우터/4.jpg",
    "category": "outerwear",
    "name": "Two-tone Track Jacket",
    "color": "dark grey and dark blue",
    "style": "sporty",
    "gender": "female",
    "bodyShape": "natural",
    "length": "normal",
    "clothingPrompt": "wearing a two-tone track jacket in dark grey and dark blue with white piping, sporty and casual style"
  },
  {
    "path": "내추럴/아우터/5.jpg",
    "category": "outerwear",
    "name": "Grey Wrap Blazer",
    "color": "grey",
    "style": "formal",
    "gender": "female",
    "bodyShape": "natural",
    "length": "normal",
    "clothingPrompt": "wearing a grey wrap-around blazer, formal or business casual style"
  },
  {
    "path": "내추럴/아우터/6.jpg",
    "category": "outerwear",
    "name": "Beige Double-breasted Long Coat",
    "color": "beige",
    "style": "formal",
    "gender": "female",
    "bodyShape": "natural",
    "length": "long",
    "clothingPrompt": "wearing a beige double-breasted long coat, formal or classic style"
  },
  {
    "path": "내추럴/아우터/7.jpg",
    "category": "outerwear",
    "name": "Beige Trench Coat with Belt",
    "color": "beige",
    "style": "classic",
    "gender": "female",
    "bodyShape": "natural",
    "length": "long",
    "clothingPrompt": "wearing a beige trench coat with a belted waist, classic and formal style"
  },
  {
    "path": "내추럴/아우터/8.jpg",
    "category": "outerwear",
    "name": "Cream Shearling Biker Jacket",
    "color": "cream",
    "style": "casual",
    "gender": "female",
    "bodyShape": "natural",
    "length": "short",
    "clothingPrompt": "wearing a cream shearling-lined biker jacket with a belted waist, casual and warm style"
  },
  {
    "path": "내추럴/아우터/9.jpg",
    "category": "outerwear",
    "name": "Brown Shearling Collar Jacket",
    "color": "brown and cream",
    "style": "casual",
    "gender": "female",
    "bodyShape": "natural",
    "length": "short",
    "clothingPrompt": "wearing a brown leather jacket with a cream shearling collar and lining, casual and warm style"
  },
  {
    "path": "내추럴/아우터/10.jpg",
    "category": "outerwear",
    "name": "Dark Brown Leather Bomber Jacket",
    "color": "dark brown",
    "style": "casual",
    "gender": "female",
    "bodyShape": "natural",
    "length": "normal",
    "clothingPrompt": "wearing a dark brown leather bomber jacket with a classic collar and ribbed cuffs, casual streetwear style"
  },
  {
    "path": "내추럴/아우터/11.jpg",
    "category": "outerwear",
    "name": "Dark Grey Cropped Hooded Jacket",
    "color": "dark grey",
    "style": "casual",
    "gender": "female",
    "bodyShape": "natural",
    "length": "short",
    "clothingPrompt": "wearing a dark grey cropped hooded jacket with drawstring details and utility pockets, casual streetwear style"
  },
  {
    "path": "내추럴/아우터/12.jpg",
    "category": "outerwear",
    "name": "Brown Suede Belted Jacket",
    "color": "brown",
    "style": "casual",
    "gender": "female",
    "bodyShape": "natural",
    "length": "short",
    "clothingPrompt": "wearing a brown suede belted jacket with flap pockets, casual and chic style"
  },
  {
    "path": "내추럴/아우터/13.jpg",
    "category": "outerwear",
    "name": "Brown Plaid Cropped Jacket",
    "color": "brown",
    "style": "casual",
    "gender": "female",
    "bodyShape": "natural",
    "length": "short",
    "clothingPrompt": "wearing a brown plaid cropped jacket with a collar and button closure, casual chic style"
  },
  {
    "path": "내추럴/아우터/14.jpg",
    "category": "outerwear",
    "name": "Grey Faux Fur Coat",
    "color": "grey",
    "style": "luxurious",
    "gender": "female",
    "bodyShape": "natural",
    "length": "normal",
    "clothingPrompt": "wearing a grey faux fur coat with a wide collar, luxurious and warm style"
  }
]